{
        "response": [
                {
                        "maintainer": "",
                        "oem": "",
                        "device": "",
                        "filename": "RisingOS-4.2-RELEASE-20240806-GAPPS-COMMUNI
TY-Pong-ota-signed.zip",
                        "download": "",
                        "timestamp": 1722924908,
                        "md5": "6e3765b6643ffb366444b67956f9f2dc",
                        "sha256": "d624e53e2b95e9e1495deb20b521677188af4165da38a
340cf1ef7799501bca2",
                        "size": 2822852676,
                        "version": "4.2-Kailash",
                        "buildtype": "",
                        "forum": "",
                        "gapps": "",
                        "firmware": "",
                        "modem": "",
                        "bootloader": "",
                        "recovery": "",
                        "paypal": "",
                        "telegram": "",
                        "dt": "",
                        "common-dt": "",
                        "kernel": ""
                }
        ]
}
